skyward_api/__init__.py
skyward_api/api.py
skyward_api/assignment.py
skyward_api/helpers.py
skyward_api/skyward_class.py
skyward_api-1.7.0.dist-info/METADATA
skyward_api-1.7.0.dist-info/RECORD
skyward_api-1.7.0.dist-info/WHEEL
skyward_api-1.7.0.dist-info/top_level.txt
