Metadata-Version: 2.1
Name: skyward-api
Version: 1.7.0
Summary: Python API for Skyward
Home-page: https://github.com/ddxtanx/skyward_api
Author: Garrett Credi
Author-email: gcc@ameritech.net
License: UNKNOWN
Platform: UNKNOWN
Classifier: Development Status :: 5 - Production/Stable
Classifier: Environment :: Console
Classifier: Intended Audience :: Developers
Classifier: Natural Language :: English
Classifier: Programming Language :: Python :: 3.6
Classifier: License :: OSI Approved :: MIT License
Classifier: Operating System :: OS Independent
Classifier: Topic :: Utilities
Requires-Dist: requests-html
Requires-Dist: mypy
